langchain_couchbase/__init__.py
langchain_couchbase/cache.py
langchain_couchbase/chat_message_histories.py
langchain_couchbase/py.typed
langchain_couchbase/vectorstores/__init__.py
langchain_couchbase/vectorstores/base_vector_store.py
langchain_couchbase/vectorstores/query_vector_store.py
langchain_couchbase/vectorstores/search_vector_store.py
langchain_couchbase-1.0.1.dist-info/LICENSE
langchain_couchbase-1.0.1.dist-info/METADATA
langchain_couchbase-1.0.1.dist-info/WHEEL
langchain_couchbase-1.0.1.dist-info/RECORD
