Metadata-Version: 2.1
Name: langchain-couchbase
Version: 1.0.1
Summary: An integration package connecting Couchbase and LangChain
Home-page: https://github.com/Couchbase-Ecosystem/langchain-couchbase/
License: MIT
Author: Couchbase Developer Experience Team
Author-email: devadvocates@couchbase.com
Requires-Python: >=3.10,<4.0
Classifier: License :: OSI Approved :: MIT License
Classifier: Programming Language :: Python :: 3
Classifier: Programming Language :: Python :: 3.10
Classifier: Programming Language :: Python :: 3.11
Classifier: Programming Language :: Python :: 3.12
Classifier: Programming Language :: Python :: 3.13
Requires-Dist: couchbase (>=4.5.0,<5.0.0)
Requires-Dist: langchain-classic (>=1.0.0,<2.0.0)
Requires-Dist: langchain-core (>=1.0.7,<2.0.0)
Project-URL: Repository, https://github.com/Couchbase-Ecosystem/langchain-couchbase/
Project-URL: Release Notes, https://github.com/Couchbase-Ecosystem/langchain-couchbase/releases
Project-URL: Source Code, https://github.com/Couchbase-Ecosystem/langchain-couchbase/tree/main/langchain_couchbase
